dkg/__init__.py
dkg/assertion.py
dkg/clients/__init__.py
dkg/clients/async_dkg.py
dkg/clients/dkg.py
dkg/constants.py
dkg/data/interfaces/AskStorage.json
dkg/data/interfaces/Chronos.json
dkg/data/interfaces/Hub.json
dkg/data/interfaces/IdentityStorage.json
dkg/data/interfaces/KnowledgeCollection.json
dkg/data/interfaces/KnowledgeCollectionStorage.json
dkg/data/interfaces/Paranet.json
dkg/data/interfaces/ParanetIncentivesPoolFactory.json
dkg/data/interfaces/ParanetKnowledgeMinersRegistry.json
dkg/data/interfaces/ParanetNeuroIncentivesPool.json
dkg/data/interfaces/ParanetsRegistry.json
dkg/data/interfaces/Token.json
dkg/dataclasses.py
dkg/exceptions.py
dkg/managers/__init__.py
dkg/managers/async_manager.py
dkg/managers/manager.py
dkg/method.py
dkg/modules/__init__.py
dkg/modules/asset/__init__.py
dkg/modules/asset/asset.py
dkg/modules/asset/async_asset.py
dkg/modules/async_module.py
dkg/modules/graph/__init__.py
dkg/modules/graph/async_graph.py
dkg/modules/graph/graph.py
dkg/modules/module.py
dkg/modules/network/__init__.py
dkg/modules/network/network.py
dkg/modules/node/__init__.py
dkg/modules/node/async_node.py
dkg/modules/node/node.py
dkg/modules/paranet/__init__.py
dkg/modules/paranet/paranet.py
dkg/providers/__init__.py
dkg/providers/blockchain/__init__.py
dkg/providers/blockchain/async_blockchain.py
dkg/providers/blockchain/base_blockchain.py
dkg/providers/blockchain/blockchain.py
dkg/providers/node/__init__.py
dkg/providers/node/async_node_http.py
dkg/providers/node/base_node_http.py
dkg/providers/node/node_http.py
dkg/services/__init__.py
dkg/services/blockchain_services/__init__.py
dkg/services/blockchain_services/async_blockchain_service.py
dkg/services/blockchain_services/blockchain_service.py
dkg/services/input_service.py
dkg/services/node_services/__init__.py
dkg/services/node_services/async_node_service.py
dkg/services/node_services/node_service.py
dkg/types/__init__.py
dkg/types/blockchain.py
dkg/types/dkg_node.py
dkg/types/encoding.py
dkg/types/evm.py
dkg-8.1.0.dist-info/LICENSE
dkg-8.1.0.dist-info/METADATA
dkg-8.1.0.dist-info/NOTICE
dkg-8.1.0.dist-info/WHEEL
dkg-8.1.0.dist-info/RECORD
