Metadata-Version: 2.3
Name: dkg
Version: 8.1.0
Summary: Python library for interacting with the OriginTrail Decentralized Knowledge Graph
License: Apache-2.0
Author: Uladzislau Hubar
Author-email: hubar.uladzislau@gmail.com>, Zvonimir Sculac <zvonimir.sculac@origin-trail.com
Requires-Python: >=3.10,<4.0
Classifier: License :: OSI Approved :: Apache Software License
Classifier: Programming Language :: Python :: 3
Classifier: Programming Language :: Python :: 3.10
Classifier: Programming Language :: Python :: 3.11
Classifier: Programming Language :: Python :: 3.12
Classifier: Programming Language :: Python :: 3.13
Requires-Dist: eth-abi (>=5.1.0,<6.0.0)
Requires-Dist: eth-account (>=0.13.4,<0.14.0)
Requires-Dist: eth-typing (>=5.0.0,<6.0.0)
Requires-Dist: hexbytes (>=1.2.1,<2.0.0)
Requires-Dist: ot-pyld (>=2.1.1,<3.0.0)
Requires-Dist: pandas (>=2.2.3,<3.0.0)
Requires-Dist: python-dotenv (>=1.0.1,<2.0.0)
Requires-Dist: pyyaml (>=6.0.2,<7.0.0)
Requires-Dist: rdflib (>=6.3.2,<7.0.0)
Requires-Dist: web3 (>=7.3.0,<8.0.0)
